yaml2devops/__init__.py
yaml2devops/command_line.py
yaml2devops/core.py
yaml2devops-0.2.0.dist-info/entry_points.txt
yaml2devops-0.2.0.dist-info/WHEEL
yaml2devops-0.2.0.dist-info/METADATA
yaml2devops-0.2.0.dist-info/RECORD
